<?xml version="1.0" encoding="utf-8" ?>
<dwsync>
<file name="404.php" server="ftp.gridhost.co.uk/public_html/" local="131649920400000000" remote="131649920400000000" />
<file name="add_css.php" server="ftp.gridhost.co.uk/public_html/" local="131649920400000000" remote="131649920400000000" />
<file name="add_edit_blog.php" server="ftp.gridhost.co.uk/public_html/" local="131649920400000000" remote="131649920400000000" />
<file name="add_edit_blogusers.php" server="ftp.gridhost.co.uk/public_html/" local="131649920400000000" remote="131649920400000000" />
<file name="add_edit_business_images.php" server="ftp.gridhost.co.uk/public_html/" local="131649920400000000" remote="131649920400000000" />
<file name="add_edit_css.php" server="ftp.gridhost.co.uk/public_html/" local="131649920400000000" remote="131649920400000000" />
<file name="add_edit_customers.php" server="ftp.gridhost.co.uk/public_html/" local="131649920400000000" remote="131649920400000000" />
<file name="add_edit_events.php" server="ftp.gridhost.co.uk/public_html/" local="131649920400000000" remote="131649920400000000" />
<file name="add_edit_eventtype.php" server="ftp.gridhost.co.uk/public_html/" local="131649920400000000" remote="131649920400000000" />
<file name="add_edit_franchise.php" server="ftp.gridhost.co.uk/public_html/" local="131649920400000000" remote="131649920400000000" />
<file name="add_edit_franchise_categories.php" server="ftp.gridhost.co.uk/public_html/" local="131649920400000000" remote="131649920400000000" />
<file name="add_edit_gallery.php" server="ftp.gridhost.co.uk/public_html/" local="131649920400000000" remote="131649920400000000" />
<file name="add_edit_images.php" server="ftp.gridhost.co.uk/public_html/" local="131649920400000000" remote="131649920400000000" />
<file name="add_edit_lifestyles.php" server="ftp.gridhost.co.uk/public_html/" local="131649920400000000" remote="131649920400000000" />
<file name="add_edit_mp3songs.php" server="ftp.gridhost.co.uk/public_html/" local="131649920400000000" remote="131649920400000000" />
<file name="add_edit_news_categories.php" server="ftp.gridhost.co.uk/public_html/" local="131649920400000000" remote="131649920400000000" />
<file name="add_edit_pages.php" server="ftp.gridhost.co.uk/public_html/" local="131649920400000000" remote="131649920400000000" />
<file name="add_edit_pfolio_categories.php" server="ftp.gridhost.co.uk/public_html/" local="131649920400000000" remote="131649920400000000" />
<file name="add_edit_portfolio.php" server="ftp.gridhost.co.uk/public_html/" local="131649920400000000" remote="131649920400000000" />
<file name="add_edit_slideshow_images.php" server="ftp.gridhost.co.uk/public_html/" local="131649920400000000" remote="131649920400000000" />
<file name="add_edit_slideshows.php" server="ftp.gridhost.co.uk/public_html/" local="131649920400000000" remote="131649920400000000" />
<file name="add_edit_songlist.php" server="ftp.gridhost.co.uk/public_html/" local="131649920400000000" remote="131649920400000000" />
<file name="add_edit_templates.php" server="ftp.gridhost.co.uk/public_html/" local="131649920400000000" remote="131649920400000000" />
<file name="add_edit_testimonial.php" server="ftp.gridhost.co.uk/public_html/" local="131649920400000000" remote="131649920400000000" />
<file name="add_edit_users.php" server="ftp.gridhost.co.uk/public_html/" local="131649920400000000" remote="131649920400000000" />
<file name="add_edit_videos.php" server="ftp.gridhost.co.uk/public_html/" local="131649920400000000" remote="131649920400000000" />
<file name="add_edit_vouchers.php" server="ftp.gridhost.co.uk/public_html/" local="131649920400000000" remote="131649920400000000" />
<file name="blogusers.php" server="ftp.gridhost.co.uk/public_html/" local="131649920400000000" remote="131649920400000000" />
<file name="bulk_gallery.php" server="ftp.gridhost.co.uk/public_html/" local="131649920400000000" remote="131649920400000000" />
<file name="bulk_images.php" server="ftp.gridhost.co.uk/public_html/" local="131649920400000000" remote="131649920400000000" />
<file name="changePassword.php" server="ftp.gridhost.co.uk/public_html/" local="131649920400000000" remote="131649920400000000" />
<file name="customers.php" server="ftp.gridhost.co.uk/public_html/" local="131649920400000000" remote="131649920400000000" />
<file name="edit_franchise_news.php" server="ftp.gridhost.co.uk/public_html/" local="131649920400000000" remote="131649920400000000" />
<file name="edit_franchise_testimonial.php" server="ftp.gridhost.co.uk/public_html/" local="131649920400000000" remote="131649920400000000" />
<file name="edit_profile.php" server="ftp.gridhost.co.uk/public_html/" local="131649920400000000" remote="131649920400000000" />
<file name="enquiry.php" server="ftp.gridhost.co.uk/public_html/" local="131649920400000000" remote="131649920400000000" />
<file name="event_type.php" server="ftp.gridhost.co.uk/public_html/" local="131649920400000000" remote="131649920400000000" />
<file name="franchise_categories.php" server="ftp.gridhost.co.uk/public_html/" local="131649920400000000" remote="131649920400000000" />
<file name="franchises.php" server="ftp.gridhost.co.uk/public_html/" local="131649920400000000" remote="131649920400000000" />
<file name="home.php" server="ftp.gridhost.co.uk/public_html/" local="131649920400000000" remote="131649920400000000" />
<file name="login.php" server="ftp.gridhost.co.uk/public_html/" local="131649920400000000" remote="131649920400000000" />
<file name="logout.php" server="ftp.gridhost.co.uk/public_html/" local="131649920400000000" remote="131649920400000000" />
<file name="mailchimp.php" server="ftp.gridhost.co.uk/public_html/" local="131649920400000000" remote="131649920400000000" />
<file name="manage-blog.php" server="ftp.gridhost.co.uk/public_html/" local="131649920400000000" remote="131649920400000000" />
<file name="manage-css.php" server="ftp.gridhost.co.uk/public_html/" local="131649920400000000" remote="131649920400000000" />
<file name="manage-events.php" server="ftp.gridhost.co.uk/public_html/" local="131649920400000000" remote="131649920400000000" />
<file name="manage-gallery.php" server="ftp.gridhost.co.uk/public_html/" local="131649920400000000" remote="131649920400000000" />
<file name="manage-images.php" server="ftp.gridhost.co.uk/public_html/" local="131649920400000000" remote="131649920400000000" />
<file name="manage-lifestyles.php" server="ftp.gridhost.co.uk/public_html/" local="131649920400000000" remote="131649920400000000" />
<file name="manage-mp3songs.php" server="ftp.gridhost.co.uk/public_html/" local="131649920400000000" remote="131649920400000000" />
<file name="manage-pages.php" server="ftp.gridhost.co.uk/public_html/" local="131649920400000000" remote="131649920400000000" />
<file name="manage-portfolio.php" server="ftp.gridhost.co.uk/public_html/" local="131649920400000000" remote="131649920400000000" />
<file name="manage-songlist.php" server="ftp.gridhost.co.uk/public_html/" local="131649920400000000" remote="131649920400000000" />
<file name="manage-templates.php" server="ftp.gridhost.co.uk/public_html/" local="131649920400000000" remote="131649920400000000" />
<file name="manage-testimonial.php" server="ftp.gridhost.co.uk/public_html/" local="131649920400000000" remote="131649920400000000" />
<file name="manage-videos.php" server="ftp.gridhost.co.uk/public_html/" local="131649920400000000" remote="131649920400000000" />
<file name="news_categories.php" server="ftp.gridhost.co.uk/public_html/" local="131649920400000000" remote="131649920400000000" />
<file name="payment_customer.php" server="ftp.gridhost.co.uk/public_html/" local="131649920400000000" remote="131649920400000000" />
<file name="payment_customer_create.php" server="ftp.gridhost.co.uk/public_html/" local="131649920400000000" remote="131649920400000000" />
<file name="payment_subscription.php" server="ftp.gridhost.co.uk/public_html/" local="131649920400000000" remote="131649920400000000" />
<file name="pfolio_categories.php" server="ftp.gridhost.co.uk/public_html/" local="131649920400000000" remote="131649920400000000" />
<file name="sale_customer.php" server="ftp.gridhost.co.uk/public_html/" local="131649920400000000" remote="131649920400000000" />
<file name="settings.php" server="ftp.gridhost.co.uk/public_html/" local="131649920400000000" remote="131649920400000000" />
<file name="slideshows.php" server="ftp.gridhost.co.uk/public_html/" local="131649920400000000" remote="131649920400000000" />
<file name="users.php" server="ftp.gridhost.co.uk/public_html/" local="131649920400000000" remote="131649920400000000" />
<file name="vouchers.php" server="ftp.gridhost.co.uk/public_html/" local="131649920400000000" remote="131649920400000000" />
</dwsync>